LICENSE
README.md
setup.cfg
setup.py
PyLibSuitETECSA/__about__.py
PyLibSuitETECSA/__init__.py
PyLibSuitETECSA/api.py
PyLibSuitETECSA.egg-info/PKG-INFO
PyLibSuitETECSA.egg-info/SOURCES.txt
PyLibSuitETECSA.egg-info/dependency_links.txt
PyLibSuitETECSA.egg-info/requires.txt
PyLibSuitETECSA.egg-info/top_level.txt
PyLibSuitETECSA/core/__init__.py
PyLibSuitETECSA/core/exception.py
PyLibSuitETECSA/core/models.py
PyLibSuitETECSA/core/protocol.py
PyLibSuitETECSA/core/session.py
PyLibSuitETECSA/utils/__init__.py
PyLibSuitETECSA/utils/from_str.py
PyLibSuitETECSA/utils/parser.py
test/test_nauta.py
test/test_user_portal.py