Metadata-Version: 2.1
Name: PyLibSuitETECSA
Version: 1.0.0b1
Summary: Una API que interactúa con los servicios web de ETECSA. 
Home-page: https://github.com/SuitETECSA/PyLibSuitETECSA
Author: lesclaz
Author-email: lesclaz95@gmail.com
License: MIT
Keywords: ETECSA nauta tools
Platform: Unix
Classifier: Topic :: Internet
Classifier: License :: OSI Approved :: MIT License
Classifier: Programming Language :: Python :: 3
Classifier: Development Status :: 4 - Beta
Classifier: Operating System :: Unix
License-File: LICENSE
